pypassage/__init__.py
pypassage/reference.py
pypassage/bibledata/__init__.py
pypassage/bibledata/apidotbibles.py
pypassage/bibledata/common.py
pypassage/bibledata/esv.py
pypassage/bibledata/osis.py
pypassage/bibledata/text_cache.py
pypassage-1.3.1.dist-info/LICENSE
pypassage-1.3.1.dist-info/METADATA
pypassage-1.3.1.dist-info/WHEEL
pypassage-1.3.1.dist-info/top_level.txt
pypassage-1.3.1.dist-info/RECORD
