Metadata-Version: 2.1
Name: pypassage
Version: 1.3.1
Summary: Python module for working with bible references
Home-page: https://github.com/col16/pypassage
Author: Cameron Oliver
Author-email: cameron.oliver@gmail.com
License: UNKNOWN
Platform: UNKNOWN
Classifier: Programming Language :: Python
Classifier: Programming Language :: Python :: 2.7
Classifier: Programming Language :: Python :: 3.6
Classifier: License :: OSI Approved :: ISC License (ISCL)
Classifier: Operating System :: OS Independent
Classifier: Development Status :: 4 - Beta
Classifier: Intended Audience :: Developers
Classifier: Topic :: Software Development :: Libraries
Classifier: Topic :: Software Development :: Libraries :: Python Modules
Classifier: Topic :: Religion
Requires-Dist: future
